piim/__init__.py
piim/piim.py
pip_install_if_missing-0.0.5.dist-info/LICENSE
pip_install_if_missing-0.0.5.dist-info/METADATA
pip_install_if_missing-0.0.5.dist-info/WHEEL
pip_install_if_missing-0.0.5.dist-info/top_level.txt
pip_install_if_missing-0.0.5.dist-info/zip-safe
pip_install_if_missing-0.0.5.dist-info/RECORD
